vectara/__init__.py
vectara/agent_events/__init__.py
vectara/agent_events/client.py
vectara/agent_events/raw_client.py
vectara/agent_events/types/__init__.py
vectara/agent_events/types/agent_events_create_response.py
vectara/agent_events/types/agent_events_create_stream_response.py
vectara/agent_sessions/__init__.py
vectara/agent_sessions/client.py
vectara/agent_sessions/raw_client.py
vectara/agents/__init__.py
vectara/agents/client.py
vectara/agents/raw_client.py
vectara/api_keys/__init__.py
vectara/api_keys/client.py
vectara/api_keys/raw_client.py
vectara/app_clients/__init__.py
vectara/app_clients/client.py
vectara/app_clients/raw_client.py
vectara/auth/__init__.py
vectara/auth/client.py
vectara/auth/raw_client.py
vectara/auth/types/__init__.py
vectara/auth/types/get_token_response.py
vectara/base_client.py
vectara/chats/__init__.py
vectara/chats/client.py
vectara/chats/raw_client.py
vectara/chats/types/__init__.py
vectara/chats/types/chats_create_response.py
vectara/chats/types/chats_create_stream_response.py
vectara/chats/types/chats_create_turns_response.py
vectara/chats/types/chats_create_turns_stream_response.py
vectara/client.py
vectara/config/__init__.py
vectara/config/config.py
vectara/core/__init__.py
vectara/core/api_error.py
vectara/core/client_wrapper.py
vectara/core/datetime_utils.py
vectara/core/file.py
vectara/core/force_multipart.py
vectara/core/http_client.py
vectara/core/http_response.py
vectara/core/jsonable_encoder.py
vectara/core/oauth_token_provider.py
vectara/core/pagination.py
vectara/core/pydantic_utilities.py
vectara/core/query_encoder.py
vectara/core/remove_none_from_dict.py
vectara/core/request_options.py
vectara/core/serialization.py
vectara/corpora/__init__.py
vectara/corpora/client.py
vectara/corpora/raw_client.py
vectara/corpora/types/__init__.py
vectara/corpora/types/corpora_query_response.py
vectara/corpora/types/corpora_query_stream_response.py
vectara/corpora/types/search_corpus_parameters.py
vectara/documents/__init__.py
vectara-0.4.0.dist-info/METADATA
vectara-0.4.0.dist-info/WHEEL
vectara-0.4.0.dist-info/RECORD
